bagpipes_spacy/__init__.py
bagpipes_spacy/knowledge.py
bagpipes_spacy/normalizers.py
bagpipes_spacy/phrases.py
bagpipes_spacy-0.1.4.dist-info/METADATA
bagpipes_spacy-0.1.4.dist-info/WHEEL
bagpipes_spacy-0.1.4.dist-info/entry_points.txt
bagpipes_spacy-0.1.4.dist-info/top_level.txt
bagpipes_spacy-0.1.4.dist-info/RECORD
