Metadata-Version: 2.1
Name: bagpipes-spacy
Version: 0.1.4
Summary: A collection of spaCy components for rules-based detection and extraction.
Home-page: https://github.com/wjbmattingly/bagpipes-spacy
Author: WJB Mattingly
Classifier: Development Status :: 3 - Alpha
Classifier: Intended Audience :: Developers
Classifier: Intended Audience :: Science/Research
Classifier: License :: OSI Approved :: MIT License
Classifier: Programming Language :: Python :: 3
Classifier: Programming Language :: Python :: 3.7
Classifier: Programming Language :: Python :: 3.8
Classifier: Programming Language :: Python :: 3.9
Classifier: Programming Language :: Python :: 3.10
Classifier: Topic :: Scientific/Engineering :: Artificial Intelligence
Requires-Python: >=3.7
Requires-Dist: spacy >=3.0
